cli.py
teko_import_test-0.3.dist-info/METADATA
teko_import_test-0.3.dist-info/WHEEL
teko_import_test-0.3.dist-info/entry_points.txt
teko_import_test-0.3.dist-info/top_level.txt
teko_import_test-0.3.dist-info/RECORD
