Metadata-Version: 2.1
Name: teko-import-test
Version: 0.3
Summary: A simple commandline app for import test cases from .xlsx file
Home-page: UNKNOWN
Author: Anh Nguyen Viet
Author-email: anhvietnguyen.nva@gmail.com
License: UNKNOWN
Platform: UNKNOWN
Requires-Dist: Click
Requires-Dist: openpyxl
Requires-Dist: pandas
